moondream_station/__init__.py
moondream_station/cli.py
moondream_station/commands.py
moondream_station/completion.py
moondream_station/inference.py
moondream_station/launcher.py
moondream_station/repl.py
moondream_station/requirements.txt
moondream_station/session.py
moondream_station/session_manager.py
moondream_station/core/__init__.py
moondream_station/core/analytics.py
moondream_station/core/config.py
moondream_station/core/inference_service.py
moondream_station/core/manifest.py
moondream_station/core/manual.py
moondream_station/core/models.py
moondream_station/core/rest_server.py
moondream_station/core/service.py
moondream_station/core/simple_worker_pool.py
moondream_station/core/updater.py
moondream_station/ui/__init__.py
moondream_station/ui/display.py
moondream_station/ui/prompts.py
moondream_station_nell_02-0.1.9.dist-info/licenses/LICENSE
moondream_station_nell_02-0.1.9.dist-info/METADATA
moondream_station_nell_02-0.1.9.dist-info/WHEEL
moondream_station_nell_02-0.1.9.dist-info/entry_points.txt
moondream_station_nell_02-0.1.9.dist-info/top_level.txt
moondream_station_nell_02-0.1.9.dist-info/RECORD
